pyqadmin.py
pyqadmin-1.0.0.dist-info/WHEEL
pyqadmin-1.0.0.dist-info/METADATA
pyqadmin-1.0.0.dist-info/RECORD
