Metadata-Version: 2.1
Name: pyqadmin
Version: 1.0.0
Summary: pyqadmin
Author: queryz
Author-email: queryzram@gmail.com
Requires-Python: >=3.9,<4.0
Classifier: Programming Language :: Python :: 3
Classifier: Programming Language :: Python :: 3.9
